{
  "converted_at": 1511418849,
  "weight_encoding": "eightbit",
  "memory_layout": {
    "static": {
      "size": 90331685,
      "allocations": {
        "a83": {
          "name": "a83",
          "offset": 90331523,
          "size": 162
        },
        "a85": {
          "name": "a85",
          "offset": 7592323,
          "size": 16384
        },
        "a86": {
          "name": "a86",
          "offset": 7674243,
          "size": 16384
        },
        "a87": {
          "name": "a87",
          "offset": 7575939,
          "size": 16384
        },
        "a88": {
          "name": "a88",
          "offset": 7674243,
          "size": 16384
        },
        "a89": {
          "name": "a89",
          "offset": 7297411,
          "size": 147456
        },
        "a90": {
          "name": "a90",
          "offset": 7510403,
          "size": 16384
        },
        "a91": {
          "name": "a91",
          "offset": 7526787,
          "size": 16384
        },
        "a92": {
          "name": "a92",
          "offset": 7297411,
          "size": 147456
        },
        "a93": {
          "name": "a93",
          "offset": 7510403,
          "size": 16384
        },
        "a222": {
          "name": "a222",
          "offset": 7592323,
          "size": 16384
        },
        "a95": {
          "name": "a95",
          "offset": 7526787,
          "size": 16384
        },
        "a96": {
          "name": "a96",
          "offset": 7297411,
          "size": 147456
        },
        "a97": {
          "name": "a97",
          "offset": 7674243,
          "size": 16384
        },
        "a98": {
          "name": "a98",
          "offset": 7690627,
          "size": 16384
        },
        "a99": {
          "name": "a99",
          "offset": 7297411,
          "size": 147456
        },
        "a100": {
          "name": "a100",
          "offset": 7641475,
          "size": 16384
        },
        "a102": {
          "name": "a102",
          "offset": 7510403,
          "size": 16384
        },
        "a103": {
          "name": "a103",
          "offset": 7297411,
          "size": 147456
        },
        "a221": {
          "name": "a221",
          "offset": 7526787,
          "size": 16384
        },
        "a106": {
          "name": "a106",
          "offset": 7297411,
          "size": 147456
        },
        "a107": {
          "name": "a107",
          "offset": 7625091,
          "size": 16384
        },
        "a109": {
          "name": "a109",
          "offset": 7526787,
          "size": 16384
        },
        "a110": {
          "name": "a110",
          "offset": 7297411,
          "size": 147456
        },
        "a111": {
          "name": "a111",
          "offset": 7625091,
          "size": 16384
        },
        "a112": {
          "name": "a112",
          "offset": 7608707,
          "size": 16384
        },
        "a113": {
          "name": "a113",
          "offset": 7297411,
          "size": 147456
        },
        "a114": {
          "name": "a114",
          "offset": 7608707,
          "size": 16384
        },
        "a115": {
          "name": "a115",
          "offset": 7526787,
          "size": 16384
        },
        "a116": {
          "name": "a116",
          "offset": 7543171,
          "size": 16384
        },
        "a117": {
          "name": "a117",
          "offset": 7297411,
          "size": 147456
        },
        "a223": {
          "name": "a223",
          "offset": 7641475,
          "size": 16384
        },
        "a120": {
          "name": "a120",
          "offset": 7297411,
          "size": 147456
        },
        "a121": {
          "name": "a121",
          "offset": 7510403,
          "size": 16384
        },
        "a122": {
          "name": "a122",
          "offset": 7674243,
          "size": 16384
        },
        "a123": {
          "name": "a123",
          "offset": 7543171,
          "size": 16384
        },
        "a124": {
          "name": "a124",
          "offset": 7297411,
          "size": 147456
        },
        "a125": {
          "name": "a125",
          "offset": 7543171,
          "size": 16384
        },
        "a126": {
          "name": "a126",
          "offset": 7641475,
          "size": 16384
        },
        "a127": {
          "name": "a127",
          "offset": 7297411,
          "size": 147456
        },
        "a128": {
          "name": "a128",
          "offset": 7641475,
          "size": 16384
        },
        "a224": {
          "name": "a224",
          "offset": 7559555,
          "size": 16384
        },
        "a130": {
          "name": "a130",
          "offset": 7510403,
          "size": 16384
        },
        "a131": {
          "name": "a131",
          "offset": 7297411,
          "size": 147456
        },
        "a132": {
          "name": "a132",
          "offset": 7575939,
          "size": 16384
        },
        "a133": {
          "name": "a133",
          "offset": 7625091,
          "size": 16384
        },
        "a134": {
          "name": "a134",
          "offset": 7297411,
          "size": 147456
        },
        "a135": {
          "name": "a135",
          "offset": 7592323,
          "size": 16384
        },
        "a137": {
          "name": "a137",
          "offset": 7575939,
          "size": 16384
        },
        "a138": {
          "name": "a138",
          "offset": 7297411,
          "size": 147456
        },
        "a139": {
          "name": "a139",
          "offset": 7526787,
          "size": 16384
        },
        "a140": {
          "name": "a140",
          "offset": 7543171,
          "size": 16384
        },
        "a141": {
          "name": "a141",
          "offset": 7297411,
          "size": 147456
        },
        "a142": {
          "name": "a142",
          "offset": 7674243,
          "size": 16384
        },
        "a143": {
          "name": "a143",
          "offset": 7510403,
          "size": 16384
        },
        "a144": {
          "name": "a144",
          "offset": 7641475,
          "size": 16384
        },
        "a145": {
          "name": "a145",
          "offset": 7297411,
          "size": 147456
        },
        "a146": {
          "name": "a146",
          "offset": 7575939,
          "size": 16384
        },
        "a147": {
          "name": "a147",
          "offset": 7674243,
          "size": 16384
        },
        "a148": {
          "name": "a148",
          "offset": 7297411,
          "size": 147456
        },
        "a149": {
          "name": "a149",
          "offset": 7641475,
          "size": 16384
        },
        "a150": {
          "name": "a150",
          "offset": 7625091,
          "size": 16384
        },
        "a151": {
          "name": "a151",
          "offset": 7641475,
          "size": 16384
        },
        "a152": {
          "name": "a152",
          "offset": 7297411,
          "size": 147456
        },
        "a153": {
          "name": "a153",
          "offset": 7690627,
          "size": 16384
        },
        "a154": {
          "name": "a154",
          "offset": 7674243,
          "size": 16384
        },
        "a155": {
          "name": "a155",
          "offset": 7297411,
          "size": 147456
        },
        "a156": {
          "name": "a156",
          "offset": 7674243,
          "size": 16384
        },
        "a227": {
          "name": "a227",
          "offset": 7641475,
          "size": 16384
        },
        "a158": {
          "name": "a158",
          "offset": 7657859,
          "size": 16384
        },
        "a159": {
          "name": "a159",
          "offset": 7297411,
          "size": 147456
        },
        "a160": {
          "name": "a160",
          "offset": 7690627,
          "size": 16384
        },
        "a161": {
          "name": "a161",
          "offset": 7707011,
          "size": 16384
        },
        "a162": {
          "name": "a162",
          "offset": 7297411,
          "size": 147456
        },
        "a163": {
          "name": "a163",
          "offset": 7690627,
          "size": 16384
        },
        "a165": {
          "name": "a165",
          "offset": 7690627,
          "size": 16384
        },
        "a166": {
          "name": "a166",
          "offset": 7297411,
          "size": 147456
        },
        "a226": {
          "name": "a226",
          "offset": 7674243,
          "size": 16384
        },
        "a169": {
          "name": "a169",
          "offset": 7297411,
          "size": 147456
        },
        "a170": {
          "name": "a170",
          "offset": 7690627,
          "size": 16384
        },
        "a172": {
          "name": "a172",
          "offset": 7739779,
          "size": 16384
        },
        "a173": {
          "name": "a173",
          "offset": 7297411,
          "size": 147456
        },
        "a174": {
          "name": "a174",
          "offset": 7707011,
          "size": 16384
        },
        "a175": {
          "name": "a175",
          "offset": 7543171,
          "size": 16384
        },
        "a176": {
          "name": "a176",
          "offset": 7297411,
          "size": 147456
        },
        "a177": {
          "name": "a177",
          "offset": 7674243,
          "size": 16384
        },
        "a178": {
          "name": "a178",
          "offset": 7657859,
          "size": 16384
        },
        "a179": {
          "name": "a179",
          "offset": 7510403,
          "size": 16384
        },
        "a180": {
          "name": "a180",
          "offset": 7297411,
          "size": 147456
        },
        "a181": {
          "name": "a181",
          "offset": 7690627,
          "size": 16384
        },
        "a182": {
          "name": "a182",
          "offset": 7674243,
          "size": 16384
        },
        "a183": {
          "name": "a183",
          "offset": 7297411,
          "size": 147456
        },
        "a184": {
          "name": "a184",
          "offset": 7510403,
          "size": 16384
        },
        "a228": {
          "name": "a228",
          "offset": 7723395,
          "size": 16384
        },
        "a186": {
          "name": "a186",
          "offset": 7625091,
          "size": 16384
        },
        "a187": {
          "name": "a187",
          "offset": 7297411,
          "size": 147456
        },
        "a188": {
          "name": "a188",
          "offset": 7641475,
          "size": 16384
        },
        "a189": {
          "name": "a189",
          "offset": 7543171,
          "size": 16384
        },
        "a190": {
          "name": "a190",
          "offset": 7297411,
          "size": 147456
        },
        "a191": {
          "name": "a191",
          "offset": 7690627,
          "size": 16384
        },
        "a193": {
          "name": "a193",
          "offset": 7739779,
          "size": 16384
        },
        "a194": {
          "name": "a194",
          "offset": 7297411,
          "size": 147456
        },
        "a195": {
          "name": "a195",
          "offset": 7690627,
          "size": 16384
        },
        "a196": {
          "name": "a196",
          "offset": 7707011,
          "size": 16384
        },
        "a197": {
          "name": "a197",
          "offset": 7297411,
          "size": 147456
        },
        "a198": {
          "name": "a198",
          "offset": 7739779,
          "size": 16384
        },
        "a199": {
          "name": "a199",
          "offset": 7690627,
          "size": 16384
        },
        "a200": {
          "name": "a200",
          "offset": 7297411,
          "size": 147456
        },
        "a229": {
          "name": "a229",
          "offset": 7674243,
          "size": 16384
        },
        "a203": {
          "name": "a203",
          "offset": 7297411,
          "size": 147456
        },
        "a230": {
          "name": "a230",
          "offset": 7444867,
          "size": 65536
        },
        "a206": {
          "name": "a206",
          "offset": 7510403,
          "size": 65536
        },
        "a207": {
          "name": "a207",
          "offset": 7444867,
          "size": 65536
        },
        "a208": {
          "name": "a208",
          "offset": 6707587,
          "size": 589824
        },
        "a231": {
          "name": "a231",
          "offset": 7297411,
          "size": 262144
        },
        "a211": {
          "name": "a211",
          "offset": 6707587,
          "size": 262144
        },
        "a212": {
          "name": "a212",
          "offset": 6969731,
          "size": 262144
        },
        "a213": {
          "name": "a213",
          "offset": 4348291,
          "size": 2359296
        },
        "a232": {
          "name": "a232",
          "offset": 6707587,
          "size": 1048576
        },
        "a216": {
          "name": "a216",
          "offset": 4348291,
          "size": 1048576
        },
        "a217": {
          "name": "a217",
          "offset": 89282947,
          "size": 1048576
        },
        "a218": {
          "name": "a218",
          "offset": 4348291,
          "size": 84934656
        },
        "a219": {
          "name": "a219",
          "offset": 89282947,
          "size": 49152
        },
        "a84": {
          "name": "a84",
          "offset": 7510403,
          "size": 49152
        },
        "a1": {
          "name": "a1",
          "offset": 0,
          "size": 2654208
        },
        "a2": {
          "name": "a2",
          "offset": 2654208,
          "size": 16384
        },
        "a3": {
          "name": "a3",
          "offset": 2670592,
          "size": 36864
        },
        "a4": {
          "name": "a4",
          "offset": 2707456,
          "size": 64
        },
        "a5": {
          "name": "a5",
          "offset": 2707520,
          "size": 36864
        },
        "a6": {
          "name": "a6",
          "offset": 2744384,
          "size": 64
        },
        "a7": {
          "name": "a7",
          "offset": 2744448,
          "size": 36864
        },
        "a8": {
          "name": "a8",
          "offset": 2781312,
          "size": 64
        },
        "a9": {
          "name": "a9",
          "offset": 2781376,
          "size": 36864
        },
        "a10": {
          "name": "a10",
          "offset": 2818240,
          "size": 64
        },
        "a11": {
          "name": "a11",
          "offset": 2818304,
          "size": 36864
        },
        "a12": {
          "name": "a12",
          "offset": 2855168,
          "size": 64
        },
        "a13": {
          "name": "a13",
          "offset": 2855232,
          "size": 36864
        },
        "a14": {
          "name": "a14",
          "offset": 2892096,
          "size": 64
        },
        "a15": {
          "name": "a15",
          "offset": 2892160,
          "size": 36864
        },
        "a16": {
          "name": "a16",
          "offset": 2929024,
          "size": 64
        },
        "a17": {
          "name": "a17",
          "offset": 2929088,
          "size": 36864
        },
        "a18": {
          "name": "a18",
          "offset": 2965952,
          "size": 64
        },
        "a19": {
          "name": "a19",
          "offset": 2966016,
          "size": 36864
        },
        "a20": {
          "name": "a20",
          "offset": 3002880,
          "size": 64
        },
        "a21": {
          "name": "a21",
          "offset": 3002944,
          "size": 36864
        },
        "a22": {
          "name": "a22",
          "offset": 3039808,
          "size": 64
        },
        "a23": {
          "name": "a23",
          "offset": 3039872,
          "size": 36864
        },
        "a24": {
          "name": "a24",
          "offset": 3076736,
          "size": 64
        },
        "a25": {
          "name": "a25",
          "offset": 3076800,
          "size": 36864
        },
        "a26": {
          "name": "a26",
          "offset": 3113664,
          "size": 64
        },
        "a27": {
          "name": "a27",
          "offset": 3113728,
          "size": 36864
        },
        "a28": {
          "name": "a28",
          "offset": 3150592,
          "size": 64
        },
        "a29": {
          "name": "a29",
          "offset": 3150656,
          "size": 36864
        },
        "a30": {
          "name": "a30",
          "offset": 3187520,
          "size": 64
        },
        "a31": {
          "name": "a31",
          "offset": 3187584,
          "size": 36864
        },
        "a32": {
          "name": "a32",
          "offset": 3224448,
          "size": 64
        },
        "a33": {
          "name": "a33",
          "offset": 3224512,
          "size": 36864
        },
        "a34": {
          "name": "a34",
          "offset": 3261376,
          "size": 64
        },
        "a35": {
          "name": "a35",
          "offset": 3261440,
          "size": 36864
        },
        "a36": {
          "name": "a36",
          "offset": 3298304,
          "size": 64
        },
        "a37": {
          "name": "a37",
          "offset": 3298368,
          "size": 36864
        },
        "a38": {
          "name": "a38",
          "offset": 3335232,
          "size": 64
        },
        "a39": {
          "name": "a39",
          "offset": 3335296,
          "size": 36864
        },
        "a40": {
          "name": "a40",
          "offset": 3372160,
          "size": 64
        },
        "a41": {
          "name": "a41",
          "offset": 3372224,
          "size": 36864
        },
        "a42": {
          "name": "a42",
          "offset": 3409088,
          "size": 64
        },
        "a43": {
          "name": "a43",
          "offset": 3409152,
          "size": 36864
        },
        "a44": {
          "name": "a44",
          "offset": 3446016,
          "size": 64
        },
        "a45": {
          "name": "a45",
          "offset": 3446080,
          "size": 36864
        },
        "a46": {
          "name": "a46",
          "offset": 3482944,
          "size": 64
        },
        "a47": {
          "name": "a47",
          "offset": 3483008,
          "size": 36864
        },
        "a48": {
          "name": "a48",
          "offset": 3519872,
          "size": 64
        },
        "a49": {
          "name": "a49",
          "offset": 3519936,
          "size": 36864
        },
        "a50": {
          "name": "a50",
          "offset": 3556800,
          "size": 64
        },
        "a51": {
          "name": "a51",
          "offset": 3556864,
          "size": 36864
        },
        "a52": {
          "name": "a52",
          "offset": 3593728,
          "size": 64
        },
        "a53": {
          "name": "a53",
          "offset": 3593792,
          "size": 36864
        },
        "a54": {
          "name": "a54",
          "offset": 3630656,
          "size": 64
        },
        "a55": {
          "name": "a55",
          "offset": 3630720,
          "size": 36864
        },
        "a56": {
          "name": "a56",
          "offset": 3667584,
          "size": 64
        },
        "a57": {
          "name": "a57",
          "offset": 3667648,
          "size": 36864
        },
        "a58": {
          "name": "a58",
          "offset": 3704512,
          "size": 64
        },
        "a59": {
          "name": "a59",
          "offset": 3704576,
          "size": 36864
        },
        "a60": {
          "name": "a60",
          "offset": 3741440,
          "size": 64
        },
        "a61": {
          "name": "a61",
          "offset": 3741504,
          "size": 36864
        },
        "a62": {
          "name": "a62",
          "offset": 3778368,
          "size": 64
        },
        "a63": {
          "name": "a63",
          "offset": 3778432,
          "size": 36864
        },
        "a64": {
          "name": "a64",
          "offset": 3815296,
          "size": 64
        },
        "a65": {
          "name": "a65",
          "offset": 3815360,
          "size": 36864
        },
        "a66": {
          "name": "a66",
          "offset": 3852224,
          "size": 64
        },
        "a67": {
          "name": "a67",
          "offset": 3852288,
          "size": 36864
        },
        "a68": {
          "name": "a68",
          "offset": 3889152,
          "size": 64
        },
        "a69": {
          "name": "a69",
          "offset": 3889216,
          "size": 147456
        },
        "a70": {
          "name": "a70",
          "offset": 4036672,
          "size": 256
        },
        "a71": {
          "name": "a71",
          "offset": 4036928,
          "size": 64
        },
        "a72": {
          "name": "a72",
          "offset": 4036992,
          "size": 64
        },
        "a73": {
          "name": "a73",
          "offset": 4037056,
          "size": 147456
        },
        "a74": {
          "name": "a74",
          "offset": 4184512,
          "size": 256
        },
        "a75": {
          "name": "a75",
          "offset": 4184768,
          "size": 64
        },
        "a76": {
          "name": "a76",
          "offset": 4184832,
          "size": 64
        },
        "a77": {
          "name": "a77",
          "offset": 4184896,
          "size": 147456
        },
        "a78": {
          "name": "a78",
          "offset": 4332352,
          "size": 256
        },
        "a79": {
          "name": "a79",
          "offset": 4332608,
          "size": 64
        },
        "a80": {
          "name": "a80",
          "offset": 4332672,
          "size": 64
        },
        "a81": {
          "name": "a81",
          "offset": 4332736,
          "size": 15552
        },
        "a82": {
          "name": "a82",
          "offset": 4348288,
          "size": 3
        }
      }
    },
    "dynamic": {
      "size": 0,
      "allocations": {}
    }
  },
  "placeholders": {},
  "unresolved_value_lists": [
    [],
    [],
    [],
    [],
    [],
    [],
    [],
    [],
    [],
    [],
    [],
    [],
    [],
    [],
    [],
    [],
    [],
    [],
    [],
    [],
    [],
    [],
    [],
    [],
    [],
    [],
    [],
    [],
    [],
    [],
    [],
    [],
    [],
    [],
    [],
    [],
    [],
    [],
    [],
    [],
    [],
    [],
    [],
    [],
    [],
    [],
    [],
    [],
    [],
    [],
    [],
    [],
    [],
    [],
    [],
    [],
    [],
    [],
    [],
    [],
    [],
    [],
    [],
    [],
    [],
    [],
    [],
    [],
    [],
    [],
    [],
    [],
    [],
    [],
    [],
    [],
    [],
    [],
    [],
    [],
    [],
    [],
    [],
    [],
    [],
    [],
    [],
    [],
    [],
    [],
    [],
    [],
    [],
    [],
    [],
    [],
    [],
    [],
    [],
    [],
    [],
    [],
    [],
    [],
    [],
    [],
    [],
    [],
    [],
    [],
    [],
    [],
    [],
    [],
    [],
    [],
    [],
    [],
    [],
    [],
    [],
    [],
    [],
    [],
    [],
    [],
    [],
    [],
    [],
    [],
    [],
    [],
    [],
    [],
    [],
    []
  ],
  "inputs": [
    "a83"
  ],
  "outputs": [
    "a84"
  ],
  "licenses": {
    "webdnn": "(C) Machine Intelligence Laboratory (The University of Tokyo), MIT License",
    "eigen": "(C) Eigen authors, MPL 2.0 License"
  }
}